{"iso3":"MMR","series":{"taxrev_gdp":[{"year":1973,"value":9.4248},{"year":1974,"value":7.6223},{"year":1975,"value":7.9085},{"year":1976,"value":9.0203},{"year":1977,"value":10.4565},{"year":1978,"value":10.0094},{"year":1979,"value":10.2114},{"year":1980,"value":8.9911},{"year":1981,"value":9.2869},{"year":1982,"value":9.1961},{"year":1983,"value":8.6403},{"year":1984,"value":8.0301},{"year":1985,"value":7.7221},{"year":1986,"value":6.9331},{"year":1987,"value":5.9527},{"year":1988,"value":4.2033},{"year":1989,"value":3.9866},{"year":1990,"value":5.7976},{"year":1991,"value":5.2479},{"year":1992,"value":4.7121},{"year":1993,"value":4.5358},{"year":1994,"value":4.3084},{"year":1995,"value":3.752},{"year":1996,"value":3.9599},{"year":1997,"value":3.8327},{"year":1998,"value":3.055},{"year":1999,"value":2.3896},{"year":2000,"value":2.5751},{"year":2001,"value":1.9593},{"year":2002,"value":1.737},{"year":2003,"value":1.9188},{"year":2004,"value":2.8407},{"year":2005,"value":3.3696},{"year":2012,"value":6.3286},{"year":2013,"value":7.302},{"year":2014,"value":7.7779},{"year":2015,"value":7.4759}],"tax_inc_tax":[{"year":1973,"value":37.613},{"year":1974,"value":32.1113},{"year":1975,"value":31.7742},{"year":1976,"value":5.8385},{"year":1977,"value":7.2328},{"year":1978,"value":7.3201},{"year":1979,"value":5.2661},{"year":1980,"value":4.9043},{"year":1981,"value":4.5807},{"year":1982,"value":5.1934},{"year":1983,"value":5.7801},{"year":1984,"value":6.8029},{"year":1985,"value":7.9836},{"year":1986,"value":10.8114},{"year":1987,"value":10.9764},{"year":1988,"value":17.951},{"year":1989,"value":16.5067},{"year":1990,"value":29.7972},{"year":1991,"value":18.7977},{"year":1992,"value":25.3204},{"year":1993,"value":27.2423},{"year":1994,"value":33.5356},{"year":1995,"value":34.4153},{"year":1996,"value":29.3938},{"year":1997,"value":31.2711},{"year":1998,"value":36.2117},{"year":1999,"value":35.1096},{"year":2000,"value":34.5187},{"year":2001,"value":35.3173},{"year":2002,"value":40.5005},{"year":2003,"value":53.855},{"year":2004,"value":46.7399},{"year":2005,"value":43.3333},{"year":2013,"value":37.6298},{"year":2014,"value":37.8978},{"year":2015,"value":37.4234}],"tax_trade_tax":[{"year":1973,"value":17.5407},{"year":1974,"value":20.5703},{"year":1975,"value":25.4301},{"year":1976,"value":18.0952},{"year":1977,"value":19.0507},{"year":1978,"value":21.8347},{"year":1979,"value":24.7783},{"year":1980,"value":24.7373},{"year":1981,"value":28.6117},{"year":1982,"value":30.9865},{"year":1983,"value":26.6189},{"year":1984,"value":25.0598},{"year":1985,"value":26.1791},{"year":1986,"value":23.2686},{"year":1987,"value":23.4622},{"year":1988,"value":29.9766},{"year":1989,"value":27.2351},{"year":1990,"value":23.2877},{"year":1991,"value":27.3282},{"year":1992,"value":23.2349},{"year":1993,"value":24.2897},{"year":1994,"value":21.0189},{"year":1995,"value":20.681},{"year":1996,"value":25.6019},{"year":1997,"value":17.342},{"year":1998,"value":9.5141},{"year":1999,"value":8.9147},{"year":2000,"value":7.2444},{"year":2001,"value":7.867},{"year":2002,"value":4.704},{"year":2003,"value":2.698},{"year":2004,"value":7.2746},{"year":2005,"value":3.868},{"year":2013,"value":11.2049},{"year":2014,"value":12.8516},{"year":2015,"value":10.558}],"irai_erm":[{"year":2013,"value":1},{"year":2014,"value":1},{"year":2015,"value":2}],"v2stfisccap":[{"year":1960,"value":-0.369},{"year":1961,"value":-0.369},{"year":1962,"value":-0.369},{"year":1963,"value":-0.294},{"year":1964,"value":-0.294},{"year":1965,"value":-0.294},{"year":1966,"value":-0.294},{"year":1967,"value":-0.294},{"year":1968,"value":-0.294},{"year":1969,"value":-0.294},{"year":1970,"value":-0.294},{"year":1971,"value":-0.294},{"year":1972,"value":-0.294},{"year":1973,"value":-0.294},{"year":1974,"value":-0.294},{"year":1975,"value":-0.294},{"year":1976,"value":-0.294},{"year":1977,"value":-0.294},{"year":1978,"value":-0.294},{"year":1979,"value":-0.294},{"year":1980,"value":-0.294},{"year":1981,"value":-0.294},{"year":1982,"value":-0.294},{"year":1983,"value":-0.294},{"year":1984,"value":-0.294},{"year":1985,"value":-0.294},{"year":1986,"value":-0.294},{"year":1987,"value":-0.294},{"year":1988,"value":-0.294},{"year":1989,"value":-0.294},{"year":1990,"value":-0.294},{"year":1991,"value":-0.294},{"year":1992,"value":-0.294},{"year":1993,"value":-0.294},{"year":1994,"value":-0.294},{"year":1995,"value":-0.294},{"year":1996,"value":-0.294},{"year":1997,"value":-0.294},{"year":1998,"value":-0.294},{"year":1999,"value":-0.294},{"year":2000,"value":-0.294},{"year":2001,"value":-0.294},{"year":2002,"value":-0.294},{"year":2003,"value":-0.294},{"year":2004,"value":-0.294},{"year":2005,"value":-0.294},{"year":2006,"value":-0.294},{"year":2007,"value":-0.294},{"year":2008,"value":-0.294},{"year":2009,"value":-0.294},{"year":2010,"value":-0.276},{"year":2011,"value":0.395},{"year":2012,"value":0.395},{"year":2013,"value":0.395},{"year":2014,"value":0.395},{"year":2015,"value":0.395}],"milexpercap":[{"year":1960,"value":1.6328},{"year":1961,"value":1.5799},{"year":1962,"value":1.6087},{"year":1963,"value":1.6723},{"year":1964,"value":1.6348},{"year":1965,"value":1.6902},{"year":1966,"value":1.6579},{"year":1967,"value":1.6126},{"year":1968,"value":1.6135},{"year":1969,"value":1.6669},{"year":1970,"value":1.7052},{"year":1971,"value":1.7186},{"year":1972,"value":1.6295},{"year":1973,"value":1.8268},{"year":1974,"value":1.8481},{"year":1975,"value":1.7117},{"year":1976,"value":1.7841},{"year":1977,"value":1.8383},{"year":1978,"value":1.8872},{"year":1979,"value":1.9022},{"year":1980,"value":1.9322},{"year":1981,"value":1.9271},{"year":1982,"value":1.867},{"year":1983,"value":1.8352},{"year":1984,"value":1.8029},{"year":1985,"value":1.8215},{"year":1986,"value":1.9446},{"year":1987,"value":1.8194},{"year":1988,"value":1.9971},{"year":1989,"value":2.6747},{"year":1990,"value":3.0298},{"year":1991,"value":3.1572},{"year":1992,"value":3.5062},{"year":1993,"value":3.8933},{"year":1994,"value":4.1834},{"year":1995,"value":4.5061},{"year":1996,"value":4.6651},{"year":1997,"value":4.6744},{"year":1998,"value":4.8657},{"year":1999,"value":5.0206},{"year":2000,"value":5.2694},{"year":2001,"value":5.3053},{"year":2002,"value":5.445},{"year":2003,"value":6.2213},{"year":2004,"value":6.4228},{"year":2005,"value":6.5136},{"year":2006,"value":4.9998},{"year":2007,"value":4.9576},{"year":2010,"value":3.5786},{"year":2011,"value":3.8787},{"year":2012,"value":3.7918},{"year":2013,"value":3.8426},{"year":2014,"value":3.837},{"year":2015,"value":3.901}],"milpercap":[{"year":1960,"value":1.5335},{"year":1961,"value":1.6198},{"year":1962,"value":1.6875},{"year":1963,"value":1.7095},{"year":1964,"value":1.8223},{"year":1965,"value":1.8691},{"year":1966,"value":1.8623},{"year":1967,"value":1.8488},{"year":1968,"value":1.829},{"year":1969,"value":2.0142},{"year":1970,"value":1.9989},{"year":1971,"value":1.9837},{"year":1972,"value":2.0393},{"year":1973,"value":2.0505},{"year":1974,"value":2.0479},{"year":1975,"value":2.0577},{"year":1976,"value":2.042},{"year":1977,"value":2.0142},{"year":1978,"value":2.0114},{"year":1979,"value":1.9922},{"year":1980,"value":1.8294},{"year":1981,"value":1.9465},{"year":1982,"value":1.9281},{"year":1983,"value":1.7758},{"year":1984,"value":1.7682},{"year":1985,"value":1.7746},{"year":1986,"value":1.759},{"year":1987,"value":1.744},{"year":1988,"value":1.7299},{"year":1989,"value":1.7767},{"year":1990,"value":1.8816},{"year":1991,"value":2.0576},{"year":1992,"value":2.047},{"year":1993,"value":2.141},{"year":1994,"value":2.1309},{"year":1995,"value":2.1204},{"year":1996,"value":2.1095},{"year":1997,"value":2.0982},{"year":1998,"value":2.0869},{"year":1999,"value":2.1366},{"year":2000,"value":2.1238},{"year":2001,"value":2.1144},{"year":2002,"value":2.3329},{"year":2003,"value":2.4101},{"year":2004,"value":2.3448},{"year":2005,"value":2.2766},{"year":2006,"value":2.1549},{"year":2007,"value":2.1468},{"year":2008,"value":2.2117},{"year":2009,"value":2.206},{"year":2010,"value":2.1998},{"year":2011,"value":2.193},{"year":2012,"value":2.1857},{"year":2013,"value":2.3886},{"year":2014,"value":2.3811},{"year":2015,"value":2.3742}],"policecap":[{"year":2001,"value":0.8795},{"year":2002,"value":0.8754},{"year":2011,"value":0.8309},{"year":2012,"value":0.8353},{"year":2013,"value":0.8571},{"year":2014,"value":0.8687},{"year":2015,"value":0.875}],"bti_mo":[{"year":2006,"value":6},{"year":2007,"value":7},{"year":2008,"value":8},{"year":2009,"value":7},{"year":2010,"value":6},{"year":2011,"value":6},{"year":2012,"value":6},{"year":2013,"value":6},{"year":2014,"value":6},{"year":2015,"value":6}],"v2terr":[{"year":1960,"value":0.1764},{"year":1961,"value":0.2019},{"year":1962,"value":0.4959},{"year":1963,"value":0.4959},{"year":1964,"value":0.4959},{"year":1965,"value":0.4959},{"year":1966,"value":0.4959},{"year":1967,"value":0.4959},{"year":1968,"value":0.5828},{"year":1969,"value":0.5828},{"year":1970,"value":0.5828},{"year":1971,"value":0.5828},{"year":1972,"value":0.5828},{"year":1973,"value":0.5828},{"year":1974,"value":0.5828},{"year":1975,"value":0.6745},{"year":1976,"value":0.6745},{"year":1977,"value":0.6745},{"year":1978,"value":0.6745},{"year":1979,"value":0.6745},{"year":1980,"value":0.6745},{"year":1981,"value":0.6745},{"year":1982,"value":0.7323},{"year":1983,"value":0.7323},{"year":1984,"value":0.7323},{"year":1985,"value":0.7323},{"year":1986,"value":0.7323},{"year":1987,"value":0.7323},{"year":1988,"value":0.8416},{"year":1989,"value":0.9542},{"year":1990,"value":0.9542},{"year":1991,"value":0.9542},{"year":1992,"value":0.8779},{"year":1993,"value":0.8779},{"year":1994,"value":0.8779},{"year":1995,"value":0.9542},{"year":1996,"value":0.9542},{"year":1997,"value":0.9542},{"year":1998,"value":0.9542},{"year":1999,"value":0.9542},{"year":2000,"value":0.9542},{"year":2001,"value":0.649},{"year":2002,"value":0.649},{"year":2003,"value":0.649},{"year":2004,"value":0.649},{"year":2005,"value":0.649},{"year":2006,"value":0.649},{"year":2007,"value":0.6889},{"year":2008,"value":0.6889},{"year":2009,"value":0.6405},{"year":2010,"value":0.7225},{"year":2011,"value":0.7858},{"year":2012,"value":0.7858},{"year":2013,"value":0.761},{"year":2014,"value":0.7279},{"year":2015,"value":0.7279}],"StateHist50s":[{"year":1960,"value":0.6403},{"year":1961,"value":0.6425},{"year":1962,"value":0.6447},{"year":1963,"value":0.6469},{"year":1964,"value":0.6491},{"year":1965,"value":0.6512},{"year":1966,"value":0.6533},{"year":1967,"value":0.6554},{"year":1968,"value":0.6574},{"year":1969,"value":0.6594},{"year":1970,"value":0.6614},{"year":1971,"value":0.6634},{"year":1972,"value":0.6654},{"year":1973,"value":0.6673},{"year":1974,"value":0.6692},{"year":1975,"value":0.6711},{"year":1976,"value":0.673},{"year":1977,"value":0.6748},{"year":1978,"value":0.6767},{"year":1979,"value":0.6785},{"year":1980,"value":0.6803},{"year":1981,"value":0.682},{"year":1982,"value":0.6838},{"year":1983,"value":0.6855},{"year":1984,"value":0.6872},{"year":1985,"value":0.6889},{"year":1986,"value":0.6906},{"year":1987,"value":0.6922},{"year":1988,"value":0.6939},{"year":1989,"value":0.6955},{"year":1990,"value":0.6971},{"year":1991,"value":0.6987},{"year":1992,"value":0.7002},{"year":1993,"value":0.7018},{"year":1994,"value":0.7033},{"year":1995,"value":0.7049},{"year":1996,"value":0.7064},{"year":1997,"value":0.7078},{"year":1998,"value":0.7093},{"year":1999,"value":0.7108},{"year":2000,"value":0.7122},{"year":2001,"value":0.7137},{"year":2002,"value":0.7151},{"year":2003,"value":0.7165},{"year":2004,"value":0.7179},{"year":2005,"value":0.7193},{"year":2006,"value":0.7206},{"year":2007,"value":0.722},{"year":2008,"value":0.7233},{"year":2009,"value":0.7246},{"year":2010,"value":0.7259},{"year":2011,"value":0.7272},{"year":2012,"value":0.7285},{"year":2013,"value":0.7298},{"year":2014,"value":0.7311},{"year":2015,"value":0.7323}],"v2clrspct":[{"year":1960,"value":0.803},{"year":1961,"value":0.537},{"year":1962,"value":-0.952},{"year":1963,"value":-1.282},{"year":1964,"value":-2.272},{"year":1965,"value":-2.272},{"year":1966,"value":-2.272},{"year":1967,"value":-2.272},{"year":1968,"value":-2.272},{"year":1969,"value":-2.272},{"year":1970,"value":-2.272},{"year":1971,"value":-2.272},{"year":1972,"value":-2.272},{"year":1973,"value":-2.272},{"year":1974,"value":-2.272},{"year":1975,"value":-2.272},{"year":1976,"value":-2.272},{"year":1977,"value":-2.272},{"year":1978,"value":-2.272},{"year":1979,"value":-2.272},{"year":1980,"value":-2.272},{"year":1981,"value":-2.272},{"year":1982,"value":-2.272},{"year":1983,"value":-2.272},{"year":1984,"value":-2.272},{"year":1985,"value":-2.272},{"year":1986,"value":-2.272},{"year":1987,"value":-2.272},{"year":1988,"value":-2.363},{"year":1989,"value":-2.363},{"year":1990,"value":-2.371},{"year":1991,"value":-2.371},{"year":1992,"value":-2.371},{"year":1993,"value":-2.371},{"year":1994,"value":-2.371},{"year":1995,"value":-2.371},{"year":1996,"value":-2.371},{"year":1997,"value":-2.371},{"year":1998,"value":-2.371},{"year":1999,"value":-2.371},{"year":2000,"value":-1.881},{"year":2001,"value":-1.881},{"year":2002,"value":-1.881},{"year":2003,"value":-1.881},{"year":2004,"value":-1.881},{"year":2005,"value":-1.881},{"year":2006,"value":-1.881},{"year":2007,"value":-1.881},{"year":2008,"value":-1.881},{"year":2009,"value":-1.881},{"year":2010,"value":-0.96},{"year":2011,"value":-0.596},{"year":2012,"value":-0.755},{"year":2013,"value":-0.432},{"year":2014,"value":-0.35},{"year":2015,"value":0.035}],"AdmEffic":[{"year":1960,"value":3},{"year":1961,"value":3},{"year":1962,"value":3}],"irai_qbfm":[{"year":2013,"value":3},{"year":2014,"value":4},{"year":2015,"value":4}],"irai_qpa":[{"year":2013,"value":1},{"year":2014,"value":2},{"year":2015,"value":1}],"censusfreq":[{"year":1960,"value":0.2381},{"year":1961,"value":0.2381},{"year":1962,"value":0.2381},{"year":1963,"value":0.2381},{"year":1964,"value":0.2381},{"year":1965,"value":0.2381},{"year":1966,"value":0.2381},{"year":1967,"value":0.2381},{"year":1968,"value":0.2558},{"year":1969,"value":0.2764},{"year":1970,"value":0.3005},{"year":1971,"value":0.3293},{"year":1972,"value":0.3642},{"year":1973,"value":0.4074},{"year":1974,"value":0.4622},{"year":1975,"value":0.534},{"year":1976,"value":0.6322},{"year":1977,"value":0.7746},{"year":1978,"value":1},{"year":1979,"value":0.8397},{"year":1980,"value":0.7237},{"year":1981,"value":0.6358},{"year":1982,"value":0.567},{"year":1983,"value":0.5116},{"year":1984,"value":0.4661},{"year":1985,"value":0.428},{"year":1986,"value":0.3957},{"year":1987,"value":0.3679},{"year":1988,"value":0.3438},{"year":1989,"value":0.3226},{"year":1990,"value":0.3226},{"year":1991,"value":0.3226},{"year":1992,"value":0.3226},{"year":1993,"value":0.3226},{"year":1994,"value":0.3226},{"year":1995,"value":0.3226},{"year":1996,"value":0.3226},{"year":1997,"value":0.3226},{"year":1998,"value":0.3226},{"year":1999,"value":0.3226},{"year":2000,"value":0.3226},{"year":2001,"value":0.3226},{"year":2002,"value":0.3226},{"year":2003,"value":0.3226},{"year":2004,"value":0.3226},{"year":2005,"value":0.3226},{"year":2006,"value":0.3226},{"year":2007,"value":0.3226},{"year":2008,"value":0.3226},{"year":2009,"value":0.3303},{"year":2010,"value":0.3385},{"year":2011,"value":0.347},{"year":2012,"value":0.3497},{"year":2013,"value":0.3529},{"year":2014,"value":0.3571},{"year":2015,"value":0.3627}],"infcap":[{"year":1960,"value":0.3423},{"year":1961,"value":0.4564},{"year":1962,"value":0.4174},{"year":1963,"value":0.4564},{"year":1964,"value":0.4174},{"year":1965,"value":0.4564},{"year":1966,"value":0.4174},{"year":1967,"value":0.4564},{"year":1968,"value":0.4174},{"year":1969,"value":0.4123},{"year":1970,"value":0.4564},{"year":1971,"value":0.4564},{"year":1972,"value":0.4174},{"year":1973,"value":0.4457},{"year":1974,"value":0.4423},{"year":1975,"value":0.4921},{"year":1976,"value":0.4506},{"year":1977,"value":0.4457},{"year":1978,"value":0.4423},{"year":1979,"value":0.4397},{"year":1980,"value":0.4376},{"year":1981,"value":0.4356},{"year":1982,"value":0.4339},{"year":1983,"value":0.4324},{"year":1984,"value":0.4311},{"year":1985,"value":0.3902},{"year":1986,"value":0.3902},{"year":1987,"value":0.3902},{"year":1988,"value":0.3902},{"year":1989,"value":0.4921},{"year":1990,"value":0.4506},{"year":1991,"value":0.4457},{"year":1992,"value":0.4423},{"year":1993,"value":0.4787},{"year":1994,"value":0.4777},{"year":1995,"value":0.4767},{"year":1996,"value":0.4363},{"year":1997,"value":0.4752},{"year":1998,"value":0.4746},{"year":1999,"value":0.4346},{"year":2000,"value":0.4735},{"year":2001,"value":0.473},{"year":2002,"value":0.4564},{"year":2003,"value":0.4564},{"year":2004,"value":0.4564},{"year":2005,"value":0.4564},{"year":2006,"value":0.4564},{"year":2007,"value":0.4564},{"year":2008,"value":0.4564},{"year":2009,"value":0.4564},{"year":2010,"value":0.4564},{"year":2011,"value":0.4564},{"year":2012,"value":0.4174},{"year":2013,"value":0.4284},{"year":2014,"value":0.4918},{"year":2015,"value":0.477}],"wbstat":[{"year":2004,"value":0.6},{"year":2005,"value":0.6222},{"year":2006,"value":0.6111},{"year":2007,"value":0.5778},{"year":2008,"value":0.5778},{"year":2009,"value":0.4889},{"year":2010,"value":0.5222},{"year":2011,"value":0.5111},{"year":2012,"value":0.4889},{"year":2013,"value":0.5},{"year":2014,"value":0.4667},{"year":2015,"value":0.5556}]}}
