{"iso3":"SYR","series":{"taxrev_gdp":[{"year":1972,"value":11.7794},{"year":1973,"value":11.4187},{"year":1974,"value":10.0347},{"year":1975,"value":11.5017},{"year":1976,"value":11.3691},{"year":1977,"value":12.531},{"year":1978,"value":12.9612},{"year":1979,"value":10.7687},{"year":1980,"value":10.5383},{"year":1981,"value":8.877},{"year":1982,"value":12.34},{"year":1983,"value":11.96},{"year":1984,"value":12.61},{"year":1985,"value":12.99},{"year":1986,"value":12.7996},{"year":1987,"value":14.8991},{"year":1988,"value":14.3453},{"year":1989,"value":17.1294},{"year":1990,"value":16.712},{"year":1991,"value":10.8164},{"year":1992,"value":10.7365},{"year":1993,"value":10.6585},{"year":1994,"value":10.5908},{"year":1995,"value":11.8744},{"year":1996,"value":9.5099},{"year":1997,"value":10.6496},{"year":1998,"value":10.4245},{"year":1999,"value":11.3857},{"year":2000,"value":9.3758},{"year":2001,"value":9.1135},{"year":2002,"value":10.3754},{"year":2003,"value":10.9499},{"year":2004,"value":11.4773},{"year":2005,"value":10.6416},{"year":2006,"value":11.5036},{"year":2007,"value":10.7845},{"year":2008,"value":14.2724},{"year":2009,"value":14.402}],"tax_inc_tax":[{"year":1972,"value":14.5354},{"year":1973,"value":12.5222},{"year":1974,"value":15.0314},{"year":1975,"value":18.7421},{"year":1976,"value":18.2142},{"year":1977,"value":19.8523},{"year":1978,"value":21.8199},{"year":1979,"value":19.228},{"year":1980,"value":24.6715},{"year":1981,"value":31.6664},{"year":1986,"value":46.5484},{"year":1987,"value":47.9872},{"year":1988,"value":42.3358},{"year":1989,"value":39.9447},{"year":1990,"value":40.2047},{"year":1991,"value":41.543},{"year":1992,"value":35.2487},{"year":1993,"value":30.1423},{"year":1994,"value":27.4738},{"year":1995,"value":28.8858},{"year":1996,"value":32.234},{"year":1997,"value":44.4688},{"year":1998,"value":40.6553},{"year":1999,"value":43.3277},{"year":2000,"value":49.4499},{"year":2001,"value":37.2974},{"year":2002,"value":36.332},{"year":2003,"value":32.9247},{"year":2004,"value":40.6265},{"year":2005,"value":36.9846},{"year":2006,"value":32.7405},{"year":2007,"value":32.507},{"year":2008,"value":41.4619},{"year":2009,"value":50.0011}],"tax_trade_tax":[{"year":1972,"value":37.1665},{"year":1973,"value":37.0337},{"year":1974,"value":39.5597},{"year":1975,"value":40.8189},{"year":1976,"value":41.9779},{"year":1977,"value":34.4165},{"year":1978,"value":29.9667},{"year":1979,"value":35.6922},{"year":1980,"value":36.2576},{"year":1981,"value":37.044},{"year":1982,"value":24.3112},{"year":1983,"value":22.9933},{"year":1984,"value":15.6225},{"year":1985,"value":17.244},{"year":1986,"value":13.6502},{"year":1987,"value":8.6136},{"year":1988,"value":8.0108},{"year":1989,"value":9.1331},{"year":1990,"value":9.6671},{"year":1991,"value":15.1335},{"year":1992,"value":11.9447},{"year":1993,"value":18.0264},{"year":1994,"value":16.7313},{"year":1995,"value":15.8451},{"year":1996,"value":17.425},{"year":1997,"value":15.6127},{"year":1998,"value":21.8447},{"year":1999,"value":18.5837},{"year":2000,"value":16.5629},{"year":2001,"value":22.2073},{"year":2002,"value":21.8192},{"year":2003,"value":24.4746},{"year":2004,"value":21.5447},{"year":2005,"value":19.1279},{"year":2006,"value":16.5545},{"year":2007,"value":13.5617},{"year":2008,"value":9.4918},{"year":2009,"value":10.2308}],"v2stfisccap":[{"year":1960,"value":0.573},{"year":1961,"value":0.573},{"year":1962,"value":0.573},{"year":1963,"value":0.573},{"year":1964,"value":0.573},{"year":1965,"value":0.573},{"year":1966,"value":0.573},{"year":1967,"value":-0.279},{"year":1968,"value":-0.279},{"year":1969,"value":-0.279},{"year":1970,"value":-0.279},{"year":1971,"value":-0.279},{"year":1972,"value":-0.279},{"year":1973,"value":-0.279},{"year":1974,"value":-0.279},{"year":1975,"value":-0.279},{"year":1976,"value":-0.279},{"year":1977,"value":-0.279},{"year":1978,"value":-0.279},{"year":1979,"value":-0.279},{"year":1980,"value":-0.279},{"year":1981,"value":-0.279},{"year":1982,"value":-0.279},{"year":1983,"value":-0.279},{"year":1984,"value":-0.279},{"year":1985,"value":-0.279},{"year":1986,"value":-0.279},{"year":1987,"value":-0.279},{"year":1988,"value":-0.279},{"year":1989,"value":-0.279},{"year":1990,"value":-0.279},{"year":1991,"value":-0.279},{"year":1992,"value":-0.279},{"year":1993,"value":-0.279},{"year":1994,"value":-0.279},{"year":1995,"value":-0.279},{"year":1996,"value":-0.279},{"year":1997,"value":-0.279},{"year":1998,"value":-0.279},{"year":1999,"value":-0.279},{"year":2000,"value":0.528},{"year":2001,"value":0.528},{"year":2002,"value":0.528},{"year":2003,"value":0.528},{"year":2004,"value":0.528},{"year":2005,"value":0.528},{"year":2006,"value":0.528},{"year":2007,"value":0.528},{"year":2008,"value":0.528},{"year":2009,"value":0.528},{"year":2010,"value":0.528},{"year":2011,"value":0.528},{"year":2012,"value":0.346},{"year":2013,"value":-1.798},{"year":2014,"value":-1.798},{"year":2015,"value":-1.798}],"milexpercap":[{"year":1960,"value":3.0315},{"year":1961,"value":3.0011},{"year":1962,"value":3.4558},{"year":1963,"value":2.7999},{"year":1964,"value":3.1155},{"year":1965,"value":3.1343},{"year":1966,"value":2.9669},{"year":1967,"value":3.0753},{"year":1968,"value":3.497},{"year":1969,"value":3.4868},{"year":1970,"value":3.4798},{"year":1971,"value":3.3298},{"year":1972,"value":3.6703},{"year":1973,"value":4.0294},{"year":1974,"value":4.3146},{"year":1975,"value":4.7776},{"year":1976,"value":4.806},{"year":1977,"value":4.827},{"year":1978,"value":4.9875},{"year":1979,"value":5.2169},{"year":1980,"value":5.5346},{"year":1981,"value":5.5777},{"year":1982,"value":5.6537},{"year":1983,"value":5.6205},{"year":1984,"value":5.8016},{"year":1985,"value":5.8011},{"year":1986,"value":5.8151},{"year":1987,"value":5.7755},{"year":1988,"value":5.7642},{"year":1989,"value":4.8188},{"year":1990,"value":4.8897},{"year":1991,"value":5.4241},{"year":1992,"value":5.4237},{"year":1993,"value":4.6647},{"year":1994,"value":4.7732},{"year":1995,"value":4.2162},{"year":1996,"value":4.226},{"year":1997,"value":4.2483},{"year":1998,"value":4.2663},{"year":1999,"value":4.2685},{"year":2000,"value":4.0193},{"year":2001,"value":4.1269},{"year":2002,"value":4.1829},{"year":2003,"value":4.4245},{"year":2004,"value":4.368},{"year":2005,"value":4.3819},{"year":2006,"value":4.3347},{"year":2007,"value":4.3999},{"year":2008,"value":4.4407},{"year":2009,"value":4.6434},{"year":2010,"value":4.7079},{"year":2011,"value":4.782}],"milpercap":[{"year":1961,"value":2.486},{"year":1962,"value":2.4912},{"year":1963,"value":2.7661},{"year":1964,"value":2.7963},{"year":1965,"value":2.641},{"year":1966,"value":2.7348},{"year":1967,"value":2.7037},{"year":1968,"value":2.4808},{"year":1969,"value":2.5815},{"year":1970,"value":2.5502},{"year":1971,"value":2.8759},{"year":1972,"value":2.8854},{"year":1973,"value":2.853},{"year":1974,"value":2.9365},{"year":1975,"value":3.4507},{"year":1976,"value":3.4592},{"year":1977,"value":3.4662},{"year":1978,"value":3.3102},{"year":1979,"value":3.2773},{"year":1980,"value":3.3671},{"year":1981,"value":3.4072},{"year":1982,"value":3.4745},{"year":1983,"value":3.7196},{"year":1984,"value":3.6903},{"year":1985,"value":3.6572},{"year":1986,"value":3.6203},{"year":1987,"value":3.5893},{"year":1988,"value":3.5591},{"year":1989,"value":3.5296},{"year":1990,"value":3.5199},{"year":1991,"value":3.4915},{"year":1992,"value":3.4638},{"year":1993,"value":3.4365},{"year":1994,"value":3.1755},{"year":1995,"value":3.1487},{"year":1996,"value":3.1219},{"year":1997,"value":3.095},{"year":1998,"value":3.0537},{"year":1999,"value":3.0135},{"year":2000,"value":3.0084},{"year":2001,"value":3.003},{"year":2002,"value":2.9792},{"year":2003,"value":2.961},{"year":2004,"value":2.9208},{"year":2005,"value":2.8778},{"year":2006,"value":2.8426},{"year":2007,"value":2.803},{"year":2008,"value":2.7199},{"year":2009,"value":2.6958},{"year":2010,"value":2.7858},{"year":2011,"value":2.7076},{"year":2012,"value":2.7365},{"year":2013,"value":2.3117},{"year":2014,"value":2.7721},{"year":2015,"value":2.7984}],"policecap":[{"year":2003,"value":0.1088},{"year":2004,"value":0.1017}],"bti_mo":[{"year":2006,"value":14},{"year":2007,"value":15},{"year":2008,"value":16},{"year":2009,"value":15},{"year":2010,"value":14},{"year":2011,"value":14},{"year":2012,"value":14},{"year":2013,"value":8},{"year":2014,"value":2},{"year":2015,"value":1}],"v2terr":[{"year":1960,"value":1.6211},{"year":1961,"value":1.6211},{"year":1962,"value":1.6696},{"year":1963,"value":1.6696},{"year":1964,"value":1.4574},{"year":1965,"value":1.6696},{"year":1966,"value":1.6696},{"year":1967,"value":1.4574},{"year":1968,"value":1.4574},{"year":1969,"value":1.4574},{"year":1970,"value":1.5341},{"year":1971,"value":1.5341},{"year":1972,"value":1.5341},{"year":1973,"value":1.5341},{"year":1974,"value":1.5341},{"year":1975,"value":1.5341},{"year":1976,"value":1.5341},{"year":1977,"value":1.5341},{"year":1978,"value":1.5341},{"year":1979,"value":1.5341},{"year":1980,"value":1.5341},{"year":1981,"value":1.5341},{"year":1982,"value":1.5341},{"year":1983,"value":1.5341},{"year":1984,"value":1.5341},{"year":1985,"value":1.5341},{"year":1986,"value":1.5341},{"year":1987,"value":1.5341},{"year":1988,"value":1.5341},{"year":1989,"value":1.5341},{"year":1990,"value":1.5341},{"year":1991,"value":1.5341},{"year":1992,"value":1.5341},{"year":1993,"value":1.5341},{"year":1994,"value":1.5341},{"year":1995,"value":1.5341},{"year":1996,"value":1.5341},{"year":1997,"value":1.5341},{"year":1998,"value":1.5341},{"year":1999,"value":1.5341},{"year":2000,"value":1.0581},{"year":2001,"value":1.0581},{"year":2002,"value":1.0581},{"year":2003,"value":1.0581},{"year":2004,"value":1.0581},{"year":2005,"value":1.0581},{"year":2006,"value":1.0581},{"year":2007,"value":1.0581},{"year":2008,"value":1.0581},{"year":2009,"value":1.0581},{"year":2010,"value":1.0048},{"year":2011,"value":0.8871},{"year":2012,"value":0.2793},{"year":2013,"value":-0.0537},{"year":2014,"value":-0.1655},{"year":2015,"value":-0.2275}],"StateHist50s":[{"year":1960,"value":0.6063},{"year":1961,"value":0.6087},{"year":1962,"value":0.6111},{"year":1963,"value":0.6135},{"year":1964,"value":0.6159},{"year":1965,"value":0.6182},{"year":1966,"value":0.6205},{"year":1967,"value":0.6228},{"year":1968,"value":0.625},{"year":1969,"value":0.6273},{"year":1970,"value":0.6294},{"year":1971,"value":0.6316},{"year":1972,"value":0.6338},{"year":1973,"value":0.6359},{"year":1974,"value":0.638},{"year":1975,"value":0.64},{"year":1976,"value":0.6421},{"year":1977,"value":0.6441},{"year":1978,"value":0.6461},{"year":1979,"value":0.6481},{"year":1980,"value":0.65},{"year":1981,"value":0.652},{"year":1982,"value":0.6539},{"year":1983,"value":0.6558},{"year":1984,"value":0.6576},{"year":1985,"value":0.6595},{"year":1986,"value":0.6613},{"year":1987,"value":0.6631},{"year":1988,"value":0.6649},{"year":1989,"value":0.6667},{"year":1990,"value":0.6685},{"year":1991,"value":0.6702},{"year":1992,"value":0.6719},{"year":1993,"value":0.6736},{"year":1994,"value":0.6753},{"year":1995,"value":0.677},{"year":1996,"value":0.6786},{"year":1997,"value":0.6802},{"year":1998,"value":0.6818},{"year":1999,"value":0.6834},{"year":2000,"value":0.685},{"year":2001,"value":0.6866},{"year":2002,"value":0.6881},{"year":2003,"value":0.6897},{"year":2004,"value":0.6912},{"year":2005,"value":0.6927},{"year":2006,"value":0.6942},{"year":2007,"value":0.6957},{"year":2008,"value":0.6971},{"year":2009,"value":0.6986},{"year":2010,"value":0.7},{"year":2011,"value":0.7014},{"year":2012,"value":0.7029},{"year":2013,"value":0.7031},{"year":2014,"value":0.7033},{"year":2015,"value":0.7035}],"v2clrspct":[{"year":1960,"value":0.675},{"year":1961,"value":0.675},{"year":1962,"value":0.675},{"year":1963,"value":-0.163},{"year":1964,"value":-0.858},{"year":1965,"value":-0.858},{"year":1966,"value":-0.858},{"year":1967,"value":-0.858},{"year":1968,"value":-0.858},{"year":1969,"value":-0.858},{"year":1970,"value":-1.043},{"year":1971,"value":-1.26},{"year":1972,"value":-1.048},{"year":1973,"value":-1.048},{"year":1974,"value":-1.048},{"year":1975,"value":-1.048},{"year":1976,"value":-1.048},{"year":1977,"value":-1.048},{"year":1978,"value":-1.048},{"year":1979,"value":-1.478},{"year":1980,"value":-1.478},{"year":1981,"value":-1.478},{"year":1982,"value":-1.045},{"year":1983,"value":-0.788},{"year":1984,"value":-0.788},{"year":1985,"value":-0.788},{"year":1986,"value":-0.788},{"year":1987,"value":-0.788},{"year":1988,"value":-0.788},{"year":1989,"value":-0.788},{"year":1990,"value":-0.788},{"year":1991,"value":-0.788},{"year":1992,"value":-0.788},{"year":1993,"value":-0.788},{"year":1994,"value":-0.788},{"year":1995,"value":-0.788},{"year":1996,"value":-0.788},{"year":1997,"value":-0.788},{"year":1998,"value":-0.788},{"year":1999,"value":-0.788},{"year":2000,"value":-0.788},{"year":2001,"value":-0.788},{"year":2002,"value":-0.788},{"year":2003,"value":-0.788},{"year":2004,"value":-0.788},{"year":2005,"value":-0.788},{"year":2006,"value":-0.788},{"year":2007,"value":-0.788},{"year":2008,"value":-0.788},{"year":2009,"value":-0.788},{"year":2010,"value":-0.788},{"year":2011,"value":-1.728},{"year":2012,"value":-2.671},{"year":2013,"value":-2.907},{"year":2014,"value":-2.907},{"year":2015,"value":-2.907}],"AdmEffic":[{"year":1960,"value":4},{"year":1961,"value":4},{"year":1962,"value":4}],"weberian":[{"year":1970,"value":3.8},{"year":1971,"value":3.8},{"year":1972,"value":3.8},{"year":1973,"value":3.8},{"year":1974,"value":3.8},{"year":1975,"value":3.8},{"year":1976,"value":3.8},{"year":1977,"value":3.8},{"year":1978,"value":3.8},{"year":1979,"value":3.8},{"year":1980,"value":3.8},{"year":1981,"value":3.8},{"year":1982,"value":3.8},{"year":1983,"value":3.8},{"year":1984,"value":3.8},{"year":1985,"value":3.8},{"year":1986,"value":3.8},{"year":1987,"value":3.8},{"year":1988,"value":3.8},{"year":1989,"value":3.8},{"year":1990,"value":3.8}],"censusfreq":[{"year":1960,"value":0.8148},{"year":1961,"value":0.8462},{"year":1962,"value":0.88},{"year":1963,"value":0.9167},{"year":1964,"value":0.9565},{"year":1965,"value":1},{"year":1966,"value":0.991},{"year":1967,"value":0.9821},{"year":1968,"value":0.9735},{"year":1969,"value":0.9649},{"year":1970,"value":0.9565},{"year":1971,"value":0.9483},{"year":1972,"value":0.9402},{"year":1973,"value":0.9322},{"year":1974,"value":0.9244},{"year":1975,"value":0.9167},{"year":1976,"value":0.9091},{"year":1977,"value":0.8943},{"year":1978,"value":0.88},{"year":1979,"value":0.8661},{"year":1980,"value":0.8527},{"year":1981,"value":0.8397},{"year":1982,"value":0.8271},{"year":1983,"value":0.8148},{"year":1984,"value":0.8029},{"year":1985,"value":0.7914},{"year":1986,"value":0.7801},{"year":1987,"value":0.7692},{"year":1988,"value":0.7692},{"year":1989,"value":0.7857},{"year":1990,"value":0.8029},{"year":1991,"value":0.8209},{"year":1992,"value":0.8397},{"year":1993,"value":0.8594},{"year":1994,"value":0.88},{"year":1995,"value":0.9016},{"year":1996,"value":0.9244},{"year":1997,"value":0.9483},{"year":1998,"value":0.9735},{"year":1999,"value":1},{"year":2000,"value":0.9649},{"year":2001,"value":0.9322},{"year":2002,"value":0.9016},{"year":2003,"value":0.873},{"year":2004,"value":0.8462},{"year":2005,"value":0.8209},{"year":2006,"value":0.7971},{"year":2007,"value":0.7746},{"year":2008,"value":0.7534},{"year":2009,"value":0.7333},{"year":2010,"value":0.7143},{"year":2011,"value":0.7143},{"year":2012,"value":0.7143},{"year":2013,"value":0.7143},{"year":2014,"value":0.7143},{"year":2015,"value":0.7143}],"wbstat":[{"year":2004,"value":0.5778},{"year":2005,"value":0.6111},{"year":2006,"value":0.6111},{"year":2007,"value":0.5667},{"year":2008,"value":0.6222},{"year":2009,"value":0.5444},{"year":2010,"value":0.5667},{"year":2011,"value":0.6},{"year":2012,"value":0.5222},{"year":2013,"value":0.4333},{"year":2014,"value":0.4444},{"year":2015,"value":0.4778}]}}
